indico_sixpay/__about__.py
indico_sixpay/__init__.py
indico_sixpay/blueprint.py
indico_sixpay/plugin.py
indico_sixpay/request_handlers.py
indico_sixpay/utility.py
indico_sixpay/templates/event_payment_form.html
indico_sixpay-2.0.2.dist-info/DESCRIPTION.rst
indico_sixpay-2.0.2.dist-info/METADATA
indico_sixpay-2.0.2.dist-info/RECORD
indico_sixpay-2.0.2.dist-info/WHEEL
indico_sixpay-2.0.2.dist-info/entry_points.txt
indico_sixpay-2.0.2.dist-info/metadata.json
indico_sixpay-2.0.2.dist-info/top_level.txt
