Metadata-Version: 2.0
Name: indico-sixpay
Version: 2.0.2
Summary: Indico EPayment Plugin for SixPay services
Home-page: https://github.com/maxfischer2781/indico_sixpay
Author: Max Fischer
Author-email: maxfischer2781@gmail.com
License: GPLv3+
Keywords: indico epayment six sixpay plugin
Platform: UNKNOWN
Classifier: Development Status :: 5 - Production/Stable
Classifier: Environment :: Plugins
Classifier: Environment :: Web Environment
Classifier: Intended Audience :: Science/Research
Classifier: Intended Audience :: System Administrators
Classifier: Intended Audience :: Other Audience
Classifier: License :: OSI Approved :: GNU General Public License v3 or later (GPLv3+)
Classifier: Operating System :: OS Independent
Classifier: Programming Language :: Python :: 2.7
Classifier: Topic :: Communications :: Conferencing
Classifier: Topic :: Internet :: WWW/HTTP :: WSGI :: Application
Requires-Dist: requests
Requires-Dist: indico (>=2.0)
Requires-Dist: iso4217
